boldigger2/__init__.py
boldigger2/__main__.py
boldigger2/additional_data_download.py
boldigger2/digger_hit.py
boldigger2/exceptions.py
boldigger2/id_engine_coi.py
boldigger2/login.py
boldigger2-2.2.1.dist-info/LICENSE.txt
boldigger2-2.2.1.dist-info/METADATA
boldigger2-2.2.1.dist-info/WHEEL
boldigger2-2.2.1.dist-info/entry_points.txt
boldigger2-2.2.1.dist-info/top_level.txt
boldigger2-2.2.1.dist-info/RECORD
