Metadata-Version: 2.1
Name: boldigger2
Version: 2.2.1
Summary: An even better python package to query different databases of boldsystems.org
Home-page: https://github.com/DominikBuchner/BOLDigger
Author: Dominik Buchner
Author-email: dominik.buchner524@googlemail.com
License: MIT
Classifier: Programming Language :: Python :: 3
Classifier: License :: OSI Approved :: MIT License
Classifier: Operating System :: OS Independent
Requires-Python: >=3.10
License-File: LICENSE.txt
Requires-Dist: beautifulsoup4 >=4.12.3
Requires-Dist: biopython >=1.79
Requires-Dist: joblib >=1.1.0
Requires-Dist: more-itertools >=10.2.0
Requires-Dist: numpy <2.0.0,>=1.24.0
Requires-Dist: pandas >=2.2.2
Requires-Dist: Requests >=2.32.2
Requires-Dist: requests-html >=0.10.0
Requires-Dist: tqdm >=4.66.4
Requires-Dist: tqdm-joblib >=0.0.4
Requires-Dist: urllib3 >=1.26.12
Requires-Dist: tables >=3.9.2
Requires-Dist: html5lib >=1.1
Requires-Dist: lxml >=4.9.1
Requires-Dist: soupsieve >=2.5
Requires-Dist: openpyxl >=3.1.1
Requires-Dist: pyarrow >=11.0.0
Requires-Dist: lxml-html-clean >=0.1.1
Requires-Dist: free-proxy >=1.1.1
